httpie_mauth.py
httpie_mauth-0.0.4.dist-info/METADATA
httpie_mauth-0.0.4.dist-info/WHEEL
httpie_mauth-0.0.4.dist-info/entry_points.txt
httpie_mauth-0.0.4.dist-info/RECORD
