Metadata-Version: 2.1
Name: httpie-mauth
Version: 0.0.4
Summary: MAuth plugin for HTTPie
Home-page: https://github.com/masongup/httpie-mauth
License: MIT
Author: Mason Gup
Author-email: masongup@gmail.com
Requires-Python: >=3.8,<4.0
Classifier: Environment :: Web Environment
Classifier: Intended Audience :: Developers
Classifier: License :: OSI Approved :: MIT License
Classifier: Operating System :: OS Independent
Classifier: Programming Language :: Python
Classifier: Programming Language :: Python :: 3
Classifier: Programming Language :: Python :: 3.8
Classifier: Programming Language :: Python :: 3.9
Classifier: Programming Language :: Python :: 3.10
Classifier: Programming Language :: Python :: 3.11
Classifier: Topic :: Internet :: WWW/HTTP
Classifier: Topic :: Software Development :: Libraries :: Python Modules
Requires-Dist: PyYAML (>=6.0,<7.0)
Requires-Dist: httpie (>=3.0.0,<4.0.0)
Requires-Dist: mauth-client (>=1.2.1,<2.0.0)
Project-URL: Repository, https://github.com/masongup/httpie-mauth
